aws_infra_graph/__init__.py
aws_infra_graph/cli.py
aws_infra_graph/config.py
aws_infra_graph/data/__init__.py
aws_infra_graph/data/config-empty.hocon
aws_infra_graph/data_extractor.py
aws_infra_graph/graph_exporter.py
aws_infra_graph/model.py
aws_infra_graph/utils.py
aws_infra_graph-0.1.5.dist-info/entry_points.txt
aws_infra_graph-0.1.5.dist-info/WHEEL
aws_infra_graph-0.1.5.dist-info/METADATA
aws_infra_graph-0.1.5.dist-info/RECORD
